file_and_string_encryption/__init__.py
file_and_string_encryption/file_and_string_encryption.py
file_and_string_encryption-0.0.7.dist-info/LICENSE
file_and_string_encryption-0.0.7.dist-info/METADATA
file_and_string_encryption-0.0.7.dist-info/WHEEL
file_and_string_encryption-0.0.7.dist-info/top_level.txt
file_and_string_encryption-0.0.7.dist-info/RECORD
