Metadata-Version: 2.1
Name: file-and-string-encryption
Version: 0.0.7
Summary: Simple encryption functions. Do not simply trust this code! Pay attention to how you handle sensitive information!
Author: André Herber
Author-email: andre.herber.programming@gmail.com
Keywords: python
Classifier: Development Status :: 1 - Planning
Classifier: Intended Audience :: Developers
Classifier: Programming Language :: Python :: 3
Classifier: Operating System :: Unix
Classifier: Operating System :: MacOS :: MacOS X
Classifier: Operating System :: Microsoft :: Windows
License-File: LICENSE
Requires-Dist: cryptography
Requires-Dist: passlib
Requires-Dist: colorful-terminal
Requires-Dist: easy-tasks
